oco/__init__.py
oco/__main__.py
oco/app.py
oco/html.py
oco/index.py
oco/paths.py
oco/wavesurfer.py
oco/static/annotation.js
oco/static/index.js
oco/static/style.css
oco-0.0.1.dist-info/LICENSE
oco-0.0.1.dist-info/WHEEL
oco-0.0.1.dist-info/METADATA
oco-0.0.1.dist-info/RECORD
