Metadata-Version: 2.1
Name: oco
Version: 0.0.1
Summary: oco: preview audio files on your remote computer using http server with directory listing
Author-email: Vol Ky <vol@wilab.org.ua>
Classifier: License :: OSI Approved :: MIT License
Requires-Dist: fastapi
Requires-Dist: python-multipart
Requires-Dist: uvicorn
Project-URL: Home, https://github.com/proger/oco
